django_admin_mixin/__init__.py
django_admin_mixin/combiner.py
django_admin_mixin-0.1.2.dist-info/DESCRIPTION.rst
django_admin_mixin-0.1.2.dist-info/METADATA
django_admin_mixin-0.1.2.dist-info/RECORD
django_admin_mixin-0.1.2.dist-info/WHEEL
django_admin_mixin-0.1.2.dist-info/metadata.json
django_admin_mixin-0.1.2.dist-info/top_level.txt
