Metadata-Version: 2.0
Name: django-admin-mixin
Version: 0.1.2
Summary: Модуль реализует механизм примесей (mixin) для Django admin.
Home-page: https://github.com/WarmongeR1/django_admin_mixin
Author: Alexander Sapronov
Author-email: sapronov.alexander92@gmail.com
License: MIT license
Keywords: django_admin_mixin
Platform: UNKNOWN
Classifier: Development Status :: 2 - Pre-Alpha
Classifier: Intended Audience :: Developers
Classifier: License :: OSI Approved :: MIT License
Classifier: Natural Language :: English
Classifier: Programming Language :: Python :: 2
Classifier: Programming Language :: Python :: 2.6
Classifier: Programming Language :: Python :: 2.7
Classifier: Programming Language :: Python :: 3
Classifier: Programming Language :: Python :: 3.3
Classifier: Programming Language :: Python :: 3.4
Classifier: Programming Language :: Python :: 3.5
Requires-Dist: Django (>=1.6)
